CangJie/__init__.py
CangJie/constants.py
CangJie/main.py
CangJie/CTC/__init__.py
CangJie/CTC/RFAG/RFAG.py
CangJie/CTC/RFAG/__init__.py
CangJie/CTC/RFAG/Module/__init__.py
CangJie/CTC/RFAG/Module/configuration.py
CangJie/CTC/RFAG/Module/etl.py
CangJie/CTC/RFAG/Module/module.py
CangJie/CTC/RFAG/Module/run.py
CangJie/CTC/RFAG/Module/utils.py
CangJie/CTC/RFAG/Module/sym/__init__.py
CangJie/CTC/RFAG/Module/sym/fit_eval.py
CangJie/CTC/RFAG/Module/sym/viz.py
CangJie/CTC/RFAG/Module/sym/net/WCLSTM.py
CangJie/CTC/RFAG/Module/sym/net/WCRLSTM.py
CangJie/CTC/RFAG/Module/sym/net/WRCLSTM.py
CangJie/CTC/RFAG/Module/sym/net/__init__.py
CangJie/CTC/RFAG/Module/sym/net/main.py
CangJie/CTC/RFAG/Module/sym/net/net.py
CangJie/Features/__init__.py
CangJie/Features/constants.py
CangJie/Features/features.py
CangJie/Features/glyph.py
CangJie/Features/stroke.py
CangJie/SE/__init__.py
CangJie/SE/bert.py
CangJie/tokenize/__init__.py
CangJie/tokenize/tokenize.py
CangJie/utils/WVDict.py
CangJie/utils/__init__.py
CangJie/utils/embeddings.py
CangJie/utils/format.py
CangJie/utils/testing.py
CangJie-0.0.2.dist-info/DESCRIPTION.rst
CangJie-0.0.2.dist-info/METADATA
CangJie-0.0.2.dist-info/RECORD
CangJie-0.0.2.dist-info/WHEEL
CangJie-0.0.2.dist-info/entry_points.txt
CangJie-0.0.2.dist-info/metadata.json
CangJie-0.0.2.dist-info/top_level.txt
tests/__init__.py
tests/test_features.py
tests/test_tokenize/__init__.py
tests/test_tokenize/test_tokenize.py
tests/test_utils/__init__.py
tests/test_utils/conftest.py
tests/test_utils/test_embeddings.py
tests/test_utils/test_format.py
tests/test_utils/test_testing.py
tests/test_utils/test_vec_dict.py
